<annotation>
	<folder>Logo</folder>
	<filename>img52.PNG</filename>
	<path>E:\Tasks\Logo\img52.PNG</path>
	<source>
		<database>Unknown</database>
	</source>
	<size>
		<width>482</width>
		<height>367</height>
		<depth>3</depth>
	</size>
	<segmented>0</segmented>
	<object>
		<name>dbbl</name>
		<pose>Unspecified</pose>
		<truncated>0</truncated>
		<difficult>0</difficult>
		<bndbox>
			<xmin>112</xmin>
			<ymin>18</ymin>
			<xmax>169</xmax>
			<ymax>47</ymax>
		</bndbox>
	</object>
	<object>
		<name>dbbl</name>
		<pose>Unspecified</pose>
		<truncated>0</truncated>
		<difficult>0</difficult>
		<bndbox>
			<xmin>409</xmin>
			<ymin>27</ymin>
			<xmax>473</xmax>
			<ymax>93</ymax>
		</bndbox>
	</object>
</annotation>
